{
  "version": "1.0",
  "description": "한국수어(KSL) 500문장 프리셋 중 공공·의료·일상 핵심 60문장 시드셋. 출처: 국립국어원 한국수어사전 공개 목록을 기반으로 대표 어휘만 재구성. 실제 모션 glTF는 동봉 예정.",
  "source": "국립국어원 한국수어사전 (https://sldict.korean.go.kr) 공개 대표 어휘",
  "license": "CC BY-SA 2.0 KR (국립국어원 공공저작물)",
  "sentences": [
    {"id": 1, "category": "인사", "ko": "안녕하세요", "gloss": "인사", "hand": "오른손을 이마 앞에서 내려 인사"},
    {"id": 2, "category": "인사", "ko": "감사합니다", "gloss": "감사", "hand": "오른손을 가슴 위에서 앞으로"},
    {"id": 3, "category": "인사", "ko": "죄송합니다", "gloss": "미안", "hand": "주먹을 가슴에 원형으로 돌림"},
    {"id": 4, "category": "인사", "ko": "네", "gloss": "예", "hand": "주먹을 위아래로 끄덕"},
    {"id": 5, "category": "인사", "ko": "아니요", "gloss": "아니", "hand": "검지를 좌우로 흔듦"},
    {"id": 6, "category": "인사", "ko": "잘 부탁드립니다", "gloss": "부탁", "hand": "양손을 포개 앞으로"},
    {"id": 7, "category": "의료", "ko": "아파요", "gloss": "아픔", "hand": "검지를 찌르듯 두 번"},
    {"id": 8, "category": "의료", "ko": "머리가 아파요", "gloss": "머리+아픔", "hand": "머리 짚고 아픔 제스처"},
    {"id": 9, "category": "의료", "ko": "배가 아파요", "gloss": "배+아픔", "hand": "배 짚고 아픔 제스처"},
    {"id": 10, "category": "의료", "ko": "열이 나요", "gloss": "열", "hand": "이마에 손등"},
    {"id": 11, "category": "의료", "ko": "기침이 나요", "gloss": "기침", "hand": "주먹으로 입 가림"},
    {"id": 12, "category": "의료", "ko": "약을 먹었어요", "gloss": "약+먹다", "hand": "약 집어 입으로"},
    {"id": 13, "category": "의료", "ko": "예약했습니다", "gloss": "예약", "hand": "양손 검지를 꺾어 달력"},
    {"id": 14, "category": "의료", "ko": "보험증이 있습니다", "gloss": "보험증", "hand": "카드 꺼내는 제스처"},
    {"id": 15, "category": "의료", "ko": "처방전을 주세요", "gloss": "처방전", "hand": "종이 쓰는 제스처"},
    {"id": 16, "category": "관공서", "ko": "주민등록등본을 발급받고 싶습니다", "gloss": "주민등록+등본+발급", "hand": "카드 지시+문서 흔듦"},
    {"id": 17, "category": "관공서", "ko": "인감증명서를 발급받고 싶습니다", "gloss": "인감+증명", "hand": "도장+종이"},
    {"id": 18, "category": "관공서", "ko": "여권 신청하러 왔습니다", "gloss": "여권+신청", "hand": "여권 책+손 내밂"},
    {"id": 19, "category": "관공서", "ko": "운전면허 갱신하러 왔습니다", "gloss": "운전+면허+갱신", "hand": "운전+카드 뒤집"},
    {"id": 20, "category": "관공서", "ko": "세금을 내고 싶습니다", "gloss": "세금+내다", "hand": "돈 내밂"},
    {"id": 21, "category": "관공서", "ko": "번호표를 뽑았습니다", "gloss": "번호표", "hand": "티켓 뽑는 제스처"},
    {"id": 22, "category": "관공서", "ko": "창구가 어디인가요", "gloss": "창구+어디", "hand": "주변 가리킴"},
    {"id": 23, "category": "일상", "ko": "도와주세요", "gloss": "도움", "hand": "한 손을 다른 손 위에 올림"},
    {"id": 24, "category": "일상", "ko": "천천히 말해주세요", "gloss": "천천히+말하다", "hand": "손바닥을 아래로 내림"},
    {"id": 25, "category": "일상", "ko": "다시 한번 말해주세요", "gloss": "다시+말하다", "hand": "원형 회전+입"},
    {"id": 26, "category": "일상", "ko": "필담을 하고 싶어요", "gloss": "쓰다+대화", "hand": "종이 쓰는 제스처"},
    {"id": 27, "category": "일상", "ko": "수어 통역이 필요합니다", "gloss": "수어+통역", "hand": "수어 손짓+중간에 놓기"},
    {"id": 28, "category": "일상", "ko": "모르겠어요", "gloss": "모름", "hand": "어깨를 으쓱"},
    {"id": 29, "category": "일상", "ko": "알겠습니다", "gloss": "알다", "hand": "주먹 끄덕"},
    {"id": 30, "category": "일상", "ko": "잠시만요", "gloss": "잠깐", "hand": "검지를 세움"},
    {"id": 31, "category": "일상", "ko": "화장실이 어디예요", "gloss": "화장실+어디", "hand": "W모양+주변 가리킴"},
    {"id": 32, "category": "일상", "ko": "물을 주세요", "gloss": "물+주다", "hand": "컵 마시는 제스처+주기"},
    {"id": 33, "category": "일상", "ko": "배가 고파요", "gloss": "배+고픔", "hand": "배 꺼지는 제스처"},
    {"id": 34, "category": "일상", "ko": "목이 말라요", "gloss": "목+마름", "hand": "목 쓰다듬기"},
    {"id": 35, "category": "일상", "ko": "춥습니다", "gloss": "춥다", "hand": "양팔 끌어안음"},
    {"id": 36, "category": "일상", "ko": "덥습니다", "gloss": "덥다", "hand": "부채질"},
    {"id": 37, "category": "교통", "ko": "지하철을 타야 해요", "gloss": "지하철+타다", "hand": "철길+손가락 위"},
    {"id": 38, "category": "교통", "ko": "버스 정류장은 어디예요", "gloss": "버스+정류장", "hand": "버스 운전+서 있음"},
    {"id": 39, "category": "교통", "ko": "택시를 불러주세요", "gloss": "택시+부르다", "hand": "운전+손 흔들기"},
    {"id": 40, "category": "교통", "ko": "경찰을 불러주세요", "gloss": "경찰+부르다", "hand": "모자+호출"},
    {"id": 41, "category": "긴급", "ko": "119에 신고해주세요", "gloss": "119+신고", "hand": "숫자 119+전화"},
    {"id": 42, "category": "긴급", "ko": "사고가 났어요", "gloss": "사고", "hand": "충돌 제스처"},
    {"id": 43, "category": "긴급", "ko": "불이 났어요", "gloss": "불", "hand": "손가락을 펴 위로"},
    {"id": 44, "category": "긴급", "ko": "도둑이에요", "gloss": "도둑", "hand": "눈 가리고 빠져나감"},
    {"id": 45, "category": "긴급", "ko": "길을 잃었어요", "gloss": "길+잃다", "hand": "두리번거림"},
    {"id": 46, "category": "쇼핑", "ko": "얼마예요", "gloss": "얼마", "hand": "엄지와 검지 마주침"},
    {"id": 47, "category": "쇼핑", "ko": "카드로 계산할게요", "gloss": "카드+계산", "hand": "카드 내밂"},
    {"id": 48, "category": "쇼핑", "ko": "영수증 주세요", "gloss": "영수증", "hand": "종이 집기"},
    {"id": 49, "category": "쇼핑", "ko": "교환하고 싶어요", "gloss": "교환", "hand": "양손 위치 바꿈"},
    {"id": 50, "category": "쇼핑", "ko": "환불해주세요", "gloss": "환불", "hand": "되돌리는 제스처"},
    {"id": 51, "category": "은행", "ko": "입금하고 싶어요", "gloss": "입금", "hand": "돈 넣기"},
    {"id": 52, "category": "은행", "ko": "출금하고 싶어요", "gloss": "출금", "hand": "돈 꺼내기"},
    {"id": 53, "category": "은행", "ko": "통장을 새로 만들고 싶어요", "gloss": "통장+만들다", "hand": "책 펴기+만들기"},
    {"id": 54, "category": "은행", "ko": "비밀번호를 잊어버렸어요", "gloss": "비밀번호+잊다", "hand": "자물쇠+머리"},
    {"id": 55, "category": "학교", "ko": "수업에 들어갑니다", "gloss": "수업+들어가다", "hand": "책+문 안으로"},
    {"id": 56, "category": "학교", "ko": "숙제를 했어요", "gloss": "숙제", "hand": "집+연필"},
    {"id": 57, "category": "학교", "ko": "선생님께 질문하고 싶어요", "gloss": "선생님+질문", "hand": "교사+물음표"},
    {"id": 58, "category": "학교", "ko": "시험이 언제예요", "gloss": "시험+언제", "hand": "종이+손목"},
    {"id": 59, "category": "직장", "ko": "회의가 언제예요", "gloss": "회의+언제", "hand": "원형 모임+손목"},
    {"id": 60, "category": "직장", "ko": "휴가 신청하고 싶어요", "gloss": "휴가+신청", "hand": "쉬기+손 내밂"}
  ]
}
